Workbook

Sheet Summary
A1: LoRaWAN vs NB-IoT — Cost & Fit Summary | B1: LoRaWAN vs NB-IoT — Cost & Fit Summary | C1: LoRaWAN vs NB-IoT — Cost & Fit Summary | D1: LoRaWAN vs NB-IoT — Cost & Fit Summary | E1: LoRaWAN vs NB-IoT — Cost & Fit Summary | F1: LoRaWAN vs NB-IoT — Cost & Fit Summary | G1: LoRaWAN vs NB-IoT — Cost & Fit Summary | H1: LoRaWAN vs NB-IoT — Cost & Fit Summary
A2: UK planning benchmark • GBP ex VAT • 5-year default • category scenarios are independently editable | B2: UK planning benchmark • GBP ex VAT • 5-year default • category scenarios are independently editable | C2: UK planning benchmark • GBP ex VAT • 5-year default • category scenarios are independently editable | D2: UK planning benchmark • GBP ex VAT • 5-year default • category scenarios are independently editable | E2: UK planning benchmark • GBP ex VAT • 5-year default • category scenarios are independently editable | F2: UK planning benchmark • GBP ex VAT • 5-year default • category scenarios are independently editable | G2: UK planning benchmark • GBP ex VAT • 5-year default • category scenarios are independently editable | H2: UK planning benchmark • GBP ex VAT • 5-year default • category scenarios are independently editable
A4: Model headline | B4: Model headline | D4: What the model says | E4: What the model says | F4: What the model says | G4: What the model says | H4: What the model says
A5: Categories modelled | B5: =COUNTA('Category Model'!A5:A20) -> 16 | D5: At the current inputs, NB-IoT is lower cost in 15 technically viable categories and LoRaWAN in 1. The revised tariff applies £0.98 per device per month across the analysis horizon plus a £0.70 one-off fee, includes 17 MB per device per month, and charges £0.01 per excess MB. LoRaWAN can still catch up where many devices share each gateway. This remains a cost model, not a performance verdict; apply the technical gates before selection.
A6: LoRaWAN lower-cost | B6: =COUNTIF('Category Model'!AB5:AB20,"LoRaWAN") -> 1
A7: NB-IoT lower-cost | B7: =COUNTIF('Category Model'!AB5:AB20,"NB-IoT") -> 14
A8: Technically constrained | B8: =COUNTIF('Category Model'!AE5:AE20,"Technical constraint dominates cost") -> 1
A9: Default horizon | B9: =Assumptions!B5 -> 5
A12: Sensor / use case | B12: LoRa fit | C12: NB fit | D12: LoRa TCO/unit | E12: NB TCO/unit | F12: Cost winner | G12: Technical recommendation | H12: Confidence | T12: Sensor / use case | U12: LoRaWAN | V12: NB-IoT
A13: ='Category Model'!A5 -> IAQ sensors | B13: ='Category Model'!K5 -> 5 | C13: ='Category Model'!L5 -> 4 | D13: =ROUND('Category Model'!U5,2) -> 284.05 | E13: =ROUND('Category Model'!Z5,2) -> 356 | F13: ='Category Model'!AB5 -> LoRaWAN | G13: ='Category Model'!N5 -> LoRaWAN for dense estates; NB-IoT for isolated buildings | H13: ='Category Model'!O5 -> Medium | T13: =A13 -> IAQ sensors | U13: =D13 -> 284.05 | V13: =E13 -> 356
A14: ='Category Model'!A6 -> Parking bay sensors | B14: ='Category Model'!K6 -> 5 | C14: ='Category Model'!L6 -> 5 | D14: =ROUND('Category Model'!U6,2) -> #DIV/0! | E14: =ROUND('Category Model'!Z6,2) -> #DIV/0! | F14: ='Category Model'!AB6 -> NB-IoT | G14: ='Category Model'!N6 -> LoRaWAN on owned campus; NB-IoT for dispersed street assets | H14: ='Category Model'!O6 -> Medium | T14: =A14 -> Parking bay sensors | U14: =D14 -> #DIV/0! | V14: =E14 -> #DIV/0!
A15: ='Category Model'!A7 -> Room displays | B15: ='Category Model'!K7 -> 3 | C15: ='Category Model'!L7 -> 3 | D15: =ROUND('Category Model'!U7,2) -> #DIV/0! | E15: =ROUND('Category Model'!Z7,2) -> #DIV/0! | F15: ='Category Model'!AB7 -> NB-IoT | G15: ='Category Model'!N7 -> LoRaWAN for simple e-ink; Wi-Fi/Ethernet for rich displays | H15: ='Category Model'!O7 -> Low | T15: =A15 -> Room displays | U15: =D15 -> #DIV/0! | V15: =E15 -> #DIV/0!
A16: ='Category Model'!A8 -> Lux sensors | B16: ='Category Model'!K8 -> 5 | C16: ='Category Model'!L8 -> 4 | D16: =ROUND('Category Model'!U8,2) -> #DIV/0! | E16: =ROUND('Category Model'!Z8,2) -> #DIV/0! | F16: ='Category Model'!AB8 -> NB-IoT | G16: ='Category Model'!N8 -> LoRaWAN where a shared building network exists | H16: ='Category Model'!O8 -> Medium | T16: =A16 -> Lux sensors | U16: =D16 -> #DIV/0! | V16: =E16 -> #DIV/0!
A17: ='Category Model'!A9 -> Metering — electricity and water | B17: ='Category Model'!K9 -> 5 | C17: ='Category Model'!L9 -> 5 | D17: =ROUND('Category Model'!U9,2) -> #DIV/0! | E17: =ROUND('Category Model'!Z9,2) -> #DIV/0! | F17: ='Category Model'!AB9 -> NB-IoT | G17: ='Category Model'!N9 -> LoRaWAN for estates; NB-IoT for utility-style dispersed meters | H17: ='Category Model'!O9 -> High | T17: =A17 -> Metering — electricity and water | U17: =D17 -> #DIV/0! | V17: =E17 -> #DIV/0!
A18: ='Category Model'!A10 -> Fridge / process temperature | B18: ='Category Model'!K10 -> 5 | C18: ='Category Model'!L10 -> 5 | D18: =ROUND('Category Model'!U10,2) -> #DIV/0! | E18: =ROUND('Category Model'!Z10,2) -> #DIV/0! | F18: ='Category Model'!AB10 -> NB-IoT | G18: ='Category Model'!N10 -> Either; preserve local logging and alarm path | H18: ='Category Model'!O10 -> High | T18: =A18 -> Fridge / process temperature | U18: =D18 -> #DIV/0! | V18: =E18 -> #DIV/0!
A19: ='Category Model'!A11 -> Waste water monitoring | B19: ='Category Model'!K11 -> 4 | C19: ='Category Model'!L11 -> 5 | D19: =ROUND('Category Model'!U11,2) -> #DIV/0! | E19: =ROUND('Category Model'!Z11,2) -> #DIV/0! | F19: ='Category Model'!AB11 -> NB-IoT | G19: ='Category Model'!N11 -> NB-IoT usually favoured for dispersed remote assets | H19: ='Category Model'!O11 -> Medium | T19: =A19 -> Waste water monitoring | U19: =D19 -> #DIV/0! | V19: =E19 -> #DIV/0!
A20: ='Category Model'!A12 -> Water temperature | B20: ='Category Model'!K12 -> 5 | C20: ='Category Model'!L12 -> 5 | D20: =ROUND('Category Model'!U12,2) -> #DIV/0! | E20: =ROUND('Category Model'!Z12,2) -> #DIV/0! | F20: ='Category Model'!AB12 -> NB-IoT | G20: ='Category Model'!N12 -> Either; LoRaWAN when sites share coverage | H20: ='Category Model'!O12 -> High | T20: =A20 -> Water temperature | U20: =D20 -> #DIV/0! | V20: =E20 -> #DIV/0!
A21: ='Category Model'!A13 -> Water flow | B21: ='Category Model'!K13 -> 5 | C21: ='Category Model'!L13 -> 5 | D21: =ROUND('Category Model'!U13,2) -> #DIV/0! | E21: =ROUND('Category Model'!Z13,2) -> #DIV/0! | F21: ='Category Model'!AB13 -> NB-IoT | G21: ='Category Model'!N13 -> Either; NB-IoT is simpler when widely dispersed | H21: ='Category Model'!O13 -> High | T21: =A21 -> Water flow | U21: =D21 -> #DIV/0! | V21: =E21 -> #DIV/0!
A22: ='Category Model'!A14 -> Water leak detection | B22: ='Category Model'!K14 -> 5 | C22: ='Category Model'!L14 -> 5 | D22: =ROUND('Category Model'!U14,2) -> #DIV/0! | E22: =ROUND('Category Model'!Z14,2) -> #DIV/0! | F22: ='Category Model'!AB14 -> NB-IoT | G22: ='Category Model'!N14 -> LoRaWAN for density; NB-IoT for standalone premises | H22: ='Category Model'!O14 -> High | T22: =A22 -> Water leak detection | U22: =D22 -> #DIV/0! | V22: =E22 -> #DIV/0!
A23: ='Category Model'!A15 -> Acoustic sensors | B23: ='Category Model'!K15 -> 4 | C23: ='Category Model'!L15 -> 5 | D23: =ROUND('Category Model'!U15,2) -> #DIV/0! | E23: =ROUND('Category Model'!Z15,2) -> #DIV/0! | F23: ='Category Model'!AB15 -> NB-IoT | G23: ='Category Model'!N15 -> NB-IoT for dispersed water loggers; either on campus | H23: ='Category Model'!O15 -> Medium | T23: =A23 -> Acoustic sensors | U23: =D23 -> #DIV/0! | V23: =E23 -> #DIV/0!
A24: ='Category Model'!A16 -> Bin fill level — ultrasonic | B24: ='Category Model'!K16 -> 5 | C24: ='Category Model'!L16 -> 5 | D24: =ROUND('Category Model'!U16,2) -> #DIV/0! | E24: =ROUND('Category Model'!Z16,2) -> #DIV/0! | F24: ='Category Model'!AB16 -> NB-IoT | G24: ='Category Model'!N16 -> NB-IoT for citywide assets; LoRaWAN on campus/private estate | H24: ='Category Model'!O16 -> High | T24: =A24 -> Bin fill level — ultrasonic | U24: =D24 -> #DIV/0! | V24: =E24 -> #DIV/0!
A25: ='Category Model'!A18 -> Vibration sensors | B25: ='Category Model'!K18 -> 4 | C25: ='Category Model'!L18 -> 4 | D25: =ROUND('Category Model'!U18,2) -> #DIV/0! | E25: =ROUND('Category Model'!Z18,2) -> #DIV/0! | F25: ='Category Model'!AB18 -> NB-IoT | G25: ='Category Model'!N18 -> Either for features; wired/Wi-Fi/LTE for raw waveform | H25: ='Category Model'!O18 -> Medium | T25: =A25 -> Vibration sensors | U25: =D25 -> #DIV/0! | V25: =E25 -> #DIV/0!
A26: ='Category Model'!A19 -> Pressure sensors — medical gases | B26: ='Category Model'!K19 -> 4 | C26: ='Category Model'!L19 -> 4 | D26: =ROUND('Category Model'!U19,2) -> #DIV/0! | E26: =ROUND('Category Model'!Z19,2) -> #DIV/0! | F26: ='Category Model'!AB19 -> NB-IoT | G26: ='Category Model'!N19 -> LPWAN may supplement, never replace, the safety alarm system | H26: ='Category Model'!O19 -> Low | T26: =A26 -> Pressure sensors — medical gases | U26: =D26 -> #DIV/0! | V26: =E26 -> #DIV/0!
A27: ='Category Model'!A20 -> Ultrasonic non-invasive — medical gases | B27: ='Category Model'!K20 -> 4 | C27: ='Category Model'!L20 -> 4 | D27: =ROUND('Category Model'!U20,2) -> #DIV/0! | E27: =ROUND('Category Model'!Z20,2) -> #DIV/0! | F27: ='Category Model'!AB20 -> NB-IoT | G27: ='Category Model'!N20 -> Either as supplementary telemetry; validate clinical compliance | H27: ='Category Model'!O20 -> Low | T27: =A27 -> Ultrasonic non-invasive — medical gases | U27: =D27 -> #DIV/0! | V27: =E27 -> #DIV/0!

Sheet Assumptions
A1: LoRaWAN vs NB-IoT — Planning Assumptions | B1: LoRaWAN vs NB-IoT — Planning Assumptions | C1: LoRaWAN vs NB-IoT — Planning Assumptions | D1: LoRaWAN vs NB-IoT — Planning Assumptions | E1: LoRaWAN vs NB-IoT — Planning Assumptions | F1: LoRaWAN vs NB-IoT — Planning Assumptions
A2: Blue cells are editable. Costs exclude VAT and the business application/dashboard layer common to both options. | B2: Blue cells are editable. Costs exclude VAT and the business application/dashboard layer common to both options. | C2: Blue cells are editable. Costs exclude VAT and the business application/dashboard layer common to both options. | D2: Blue cells are editable. Costs exclude VAT and the business application/dashboard layer common to both options. | E2: Blue cells are editable. Costs exclude VAT and the business application/dashboard layer common to both options. | F2: Blue cells are editable. Costs exclude VAT and the business application/dashboard layer common to both options.
A4: Driver | B4: Value | C4: Unit | D4: Basis | E4: Source / evidence | F4: Sensitivity note
A5: Analysis horizon | B5: 5 | C5: years | D5: Planning assumption | F5: Change to 3, 7 or 10 years as required
A6: Gateways per site | B6: 1 | C6: gateway/site | D6: Planning assumption | F6: Survey RF coverage; resilient designs may need 2+
A7: LoRaWAN gateway hardware | B7: 415.8 | C7: £/gateway | D7: Milesight UG65 UK price | E7: https://ukiot.io/shop/ | F7: Lower-cost gateways start around £190
A8: LoRaWAN gateway installation | B8: 300 | C8: £/gateway | D8: Planning allowance | F8: Includes mounting, power and network connection
A9: LoRaWAN gateway support | B9: 60 | C9: £/gateway/year | D9: Planning allowance | F9: Remote monitoring and firmware administration
A10: LoRaWAN gateway power | B10: 22 | C10: £/gateway/year | D10: 8 W at £0.31/kWh | F10: Remove if hosted power is immaterial
A11: LoRaWAN network server | B11: 0 | C11: £/device/month | D11: Planning benchmark at scale | E11: https://aws.amazon.com/marketplace/pp/prodview-djx65iyt6w5cy | F11: Small fleets can face a fixed minimum; embedded/open-source can be lower
A12: LoRaWAN fixed platform charge | B12: 0 | C12: £/deployment/year | D12: Assumes shared or embedded server | F12: Enter vendor minimum subscription if applicable
A13: LoRaWAN device commissioning | B13: 15 | C13: £/device | D13: Planning allowance | F13: Provisioning, keys, labelling and acceptance
A14: NB-IoT monthly connectivity | B14: 0.98 | C14: £/device/month | D14: User-provided tariff | F14: Applied for every month in the analysis horizon
A15: NB-IoT SIM / activation one-off fee | B15: 0.7 | C15: £/device | D15: User-provided tariff | F15: Charged once per device
A16: NB-IoT included data | B16: 17 | C16: MB/device/month | D16: User-provided tariff | F16: Monthly allowance; overage is charged separately
A17: NB-IoT data overage | B17: 0.01 | C17: £/MB | D17: User-provided tariff | F17: Applied to monthly usage above 17 MB per device
A18: NB-IoT device commissioning | B18: 12 | C18: £/device | D18: Planning allowance | F18: SIM/eSIM activation and acceptance
A19: Annual device maintenance | B19: 2 | C19: % of hardware/year | D19: Planning allowance | F19: Excludes calibration regimes unique to the sensing application
A20: Battery service visit | B20: 35 | C20: £/device/event | D20: Planning allowance | F20: Set higher for traffic management, confined space or clinical access
A21: EUR to GBP | B21: 0.85388 | C21: £/€ | D21: ECB, 24 Jul 2026 | E21: https://www.ecb.europa.eu/stats/policy_and_exchange_rates/euro_reference_exchange_rates/html/index.en.html | F21: Update for procurement date

Sheet Category Model
A1: Category-Level Five-Year TCO | B1: Category-Level Five-Year TCO | C1: Category-Level Five-Year TCO | D1: Category-Level Five-Year TCO | E1: Category-Level Five-Year TCO | F1: Category-Level Five-Year TCO | G1: Category-Level Five-Year TCO | H1: Category-Level Five-Year TCO | I1: Category-Level Five-Year TCO | J1: Category-Level Five-Year TCO | K1: Category-Level Five-Year TCO | L1: Category-Level Five-Year TCO | M1: Category-Level Five-Year TCO | N1: Category-Level Five-Year TCO | O1: Category-Level Five-Year TCO | P1: Category-Level Five-Year TCO | Q1: Category-Level Five-Year TCO | R1: Category-Level Five-Year TCO | S1: Category-Level Five-Year TCO | T1: Category-Level Five-Year TCO | U1: Category-Level Five-Year TCO | V1: Category-Level Five-Year TCO | W1: Category-Level Five-Year TCO | X1: Category-Level Five-Year TCO | Y1: Category-Level Five-Year TCO | Z1: Category-Level Five-Year TCO | AA1: Category-Level Five-Year TCO | AB1: Category-Level Five-Year TCO | AC1: Category-Level Five-Year TCO | AD1: Category-Level Five-Year TCO | AE1: Category-Level Five-Year TCO
A2: Each row is a standalone deployment scenario. Change quantities, sites, device prices, data and battery life in blue columns. | B2: Each row is a standalone deployment scenario. Change quantities, sites, device prices, data and battery life in blue columns. | C2: Each row is a standalone deployment scenario. Change quantities, sites, device prices, data and battery life in blue columns. | D2: Each row is a standalone deployment scenario. Change quantities, sites, device prices, data and battery life in blue columns. | E2: Each row is a standalone deployment scenario. Change quantities, sites, device prices, data and battery life in blue columns. | F2: Each row is a standalone deployment scenario. Change quantities, sites, device prices, data and battery life in blue columns. | G2: Each row is a standalone deployment scenario. Change quantities, sites, device prices, data and battery life in blue columns. | H2: Each row is a standalone deployment scenario. Change quantities, sites, device prices, data and battery life in blue columns. | I2: Each row is a standalone deployment scenario. Change quantities, sites, device prices, data and battery life in blue columns. | J2: Each row is a standalone deployment scenario. Change quantities, sites, device prices, data and battery life in blue columns. | K2: Each row is a standalone deployment scenario. Change quantities, sites, device prices, data and battery life in blue columns. | L2: Each row is a standalone deployment scenario. Change quantities, sites, device prices, data and battery life in blue columns. | M2: Each row is a standalone deployment scenario. Change quantities, sites, device prices, data and battery life in blue columns. | N2: Each row is a standalone deployment scenario. Change quantities, sites, device prices, data and battery life in blue columns. | O2: Each row is a standalone deployment scenario. Change quantities, sites, device prices, data and battery life in blue columns. | P2: Each row is a standalone deployment scenario. Change quantities, sites, device prices, data and battery life in blue columns. | Q2: Each row is a standalone deployment scenario. Change quantities, sites, device prices, data and battery life in blue columns. | R2: Each row is a standalone deployment scenario. Change quantities, sites, device prices, data and battery life in blue columns. | S2: Each row is a standalone deployment scenario. Change quantities, sites, device prices, data and battery life in blue columns. | T2: Each row is a standalone deployment scenario. Change quantities, sites, device prices, data and battery life in blue columns. | U2: Each row is a standalone deployment scenario. Change quantities, sites, device prices, data and battery life in blue columns. | V2: Each row is a standalone deployment scenario. Change quantities, sites, device prices, data and battery life in blue columns. | W2: Each row is a standalone deployment scenario. Change quantities, sites, device prices, data and battery life in blue columns. | X2: Each row is a standalone deployment scenario. Change quantities, sites, device prices, data and battery life in blue columns. | Y2: Each row is a standalone deployment scenario. Change quantities, sites, device prices, data and battery life in blue columns. | Z2: Each row is a standalone deployment scenario. Change quantities, sites, device prices, data and battery life in blue columns. | AA2: Each row is a standalone deployment scenario. Change quantities, sites, device prices, data and battery life in blue columns. | AB2: Each row is a standalone deployment scenario. Change quantities, sites, device prices, data and battery life in blue columns. | AC2: Each row is a standalone deployment scenario. Change quantities, sites, device prices, data and battery life in blue columns. | AD2: Each row is a standalone deployment scenario. Change quantities, sites, device prices, data and battery life in blue columns. | AE2: Each row is a standalone deployment scenario. Change quantities, sites, device prices, data and battery life in blue columns.
A4: Sensor / use case | B4: Deployment archetype | C4: Units | D4: Sites | E4: LoRa HW £/unit | F4: NB HW £/unit | G4: Install £/unit | H4: NB data MB/month | I4: LoRa battery years | J4: NB battery years | K4: LoRa suitability (1–5) | L4: NB suitability (1–5) | M4: Required behaviour / boundary | N4: Technical recommendation | O4: Evidence confidence | P4: LoRa device capex | Q4: LoRa shared infra | R4: LoRa maintenance | S4: LoRa server variable | T4: LoRa TCO | U4: LoRa TCO/unit | V4: NB device & tariff | W4: NB data overage | X4: NB maintenance | Y4: NB TCO | Z4: NB TCO/unit | AA4: LoRa minus NB | AB4: Lower-cost option | AC4: Saving vs higher TCO | AD4: LoRa break-even units/site | AE4: Decision note
A5: IAQ sensors | B5: Indoor multi-site | C5: 1069 | D5: 1 | E5: 180 | F5: 195 | G5: 35 | H5: 14.88 | I5: 5 | J5: 3 | K5: 5 | L5: 4 | M5: Periodic CO₂/VOC/PM/temperature metadata | N5: LoRaWAN for dense estates; NB-IoT for isolated buildings | O5: Medium | P5: =C5*(E5+G5+Assumptions!$B$13) -> 245870 | Q5: =D5*Assumptions!$B$6*(Assumptions!$B$7+Assumptions!$B$8)+Assumptions!$B$5*(D5*Assumptions!$B$6*(Assumptions!$B$9+Assumptions!$B$10)+Assumptions!$B$12) -> 1125.8 | R5: =C5*E5*Assumptions!$B$19/100*Assumptions!$B$5+C5*IF(I5<=Assumptions!$B$5,Assumptions!$B$20,0) -> 56657 | S5: =C5*Assumptions!$B$11*12*Assumptions!$B$5 -> 0 | T5: =SUM(P5:S5) -> 303652.8 | U5: =ROUND(T5/C5,2) -> 284.05 | V5: =C5*(F5+G5+Assumptions!$B$18+Assumptions!$B$15+Assumptions!$B$14*12*Assumptions!$B$5) -> 322303.5 | W5: =ROUND(C5*MAX(0,H5-Assumptions!$B$16)*12*Assumptions!$B$5*Assumptions!$B$17,2) -> 0 | X5: =C5*F5*Assumptions!$B$19/100*Assumptions!$B$5+C5*IF(J5<=Assumptions!$B$5,Assumptions!$B$20,0) -> 58260.5 | Y5: =SUM(V5:X5) -> 380564 | Z5: =ROUND(Y5/C5,2) -> 356 | AA5: =ROUND(T5-Y5,2) -> -76911.2 | AB5: =IF(OR(K5<=2,L5<=2),"Not decisive",IF(T5<Y5,"LoRaWAN",IF(T5>Y5,"NB-IoT","Tie"))) -> LoRaWAN | AC5: =ABS(T5-Y5)/MAX(T5,Y5) -> 0.20209794 | AD5: =IF((Z5-U5+Q5/C5)<=0,"N/A",ROUND((Q5/D5)/(Z5-U5+Q5/C5),0)) -> 15 | AE5: =IF(OR(K5<=2,L5<=2),"Technical constraint dominates cost",IF(AB5=N5,"Cost and architecture align","Review coverage, power and support model")) -> Review coverage, power and support model
A6: Parking bay sensors | B6: Outdoor campus / street | D6: 1 | E6: 125 | F6: 140 | G6: 85 | H6: 0.2 | I6: 5 | J6: 4 | K6: 5 | L6: 5 | M6: Occupancy events and health telemetry | N6: LoRaWAN on owned campus; NB-IoT for dispersed street assets | O6: Medium | P6: =C6*(E6+G6+Assumptions!$B$13) -> 0 | Q6: =D6*Assumptions!$B$6*(Assumptions!$B$7+Assumptions!$B$8)+Assumptions!$B$5*(D6*Assumptions!$B$6*(Assumptions!$B$9+Assumptions!$B$10)+Assumptions!$B$12) -> 1125.8 | R6: =C6*E6*Assumptions!$B$19/100*Assumptions!$B$5+C6*IF(I6<=Assumptions!$B$5,Assumptions!$B$20,0) -> 0 | S6: =C6*Assumptions!$B$11*12*Assumptions!$B$5 -> 0 | T6: =SUM(P6:S6) -> 1125.8 | U6: =ROUND(T6/C6,2) -> #DIV/0! | V6: =C6*(F6+G6+Assumptions!$B$18+Assumptions!$B$15+Assumptions!$B$14*12*Assumptions!$B$5) -> 0 | W6: =ROUND(C6*MAX(0,H6-Assumptions!$B$16)*12*Assumptions!$B$5*Assumptions!$B$17,2) -> 0 | X6: =C6*F6*Assumptions!$B$19/100*Assumptions!$B$5+C6*IF(J6<=Assumptions!$B$5,Assumptions!$B$20,0) -> 0 | Y6: =SUM(V6:X6) -> 0 | Z6: =ROUND(Y6/C6,2) -> #DIV/0! | AA6: =ROUND(T6-Y6,2) -> 1125.8 | AB6: =IF(OR(K6<=2,L6<=2),"Not decisive",IF(T6<Y6,"LoRaWAN",IF(T6>Y6,"NB-IoT","Tie"))) -> NB-IoT | AC6: =ABS(T6-Y6)/MAX(T6,Y6) -> 1 | AD6: =IF((Z6-U6+Q6/C6)<=0,"N/A",ROUND((Q6/D6)/(Z6-U6+Q6/C6),0)) -> #DIV/0! | AE6: =IF(OR(K6<=2,L6<=2),"Technical constraint dominates cost",IF(AB6=N6,"Cost and architecture align","Review coverage, power and support model")) -> Review coverage, power and support model
A7: Room displays | B7: Indoor rooms | D7: 1 | E7: 200 | F7: 220 | G7: 50 | H7: 0.5 | I7: 99 | J7: 99 | K7: 3 | L7: 3 | M7: E-ink/status updates only; not rich interactive content | N7: LoRaWAN for simple e-ink; Wi-Fi/Ethernet for rich displays | O7: Low | P7: =C7*(E7+G7+Assumptions!$B$13) -> 0 | Q7: =D7*Assumptions!$B$6*(Assumptions!$B$7+Assumptions!$B$8)+Assumptions!$B$5*(D7*Assumptions!$B$6*(Assumptions!$B$9+Assumptions!$B$10)+Assumptions!$B$12) -> 1125.8 | R7: =C7*E7*Assumptions!$B$19/100*Assumptions!$B$5+C7*IF(I7<=Assumptions!$B$5,Assumptions!$B$20,0) -> 0 | S7: =C7*Assumptions!$B$11*12*Assumptions!$B$5 -> 0 | T7: =SUM(P7:S7) -> 1125.8 | U7: =ROUND(T7/C7,2) -> #DIV/0! | V7: =C7*(F7+G7+Assumptions!$B$18+Assumptions!$B$15+Assumptions!$B$14*12*Assumptions!$B$5) -> 0 | W7: =ROUND(C7*MAX(0,H7-Assumptions!$B$16)*12*Assumptions!$B$5*Assumptions!$B$17,2) -> 0 | X7: =C7*F7*Assumptions!$B$19/100*Assumptions!$B$5+C7*IF(J7<=Assumptions!$B$5,Assumptions!$B$20,0) -> 0 | Y7: =SUM(V7:X7) -> 0 | Z7: =ROUND(Y7/C7,2) -> #DIV/0! | AA7: =ROUND(T7-Y7,2) -> 1125.8 | AB7: =IF(OR(K7<=2,L7<=2),"Not decisive",IF(T7<Y7,"LoRaWAN",IF(T7>Y7,"NB-IoT","Tie"))) -> NB-IoT | AC7: =ABS(T7-Y7)/MAX(T7,Y7) -> 1 | AD7: =IF((Z7-U7+Q7/C7)<=0,"N/A",ROUND((Q7/D7)/(Z7-U7+Q7/C7),0)) -> #DIV/0! | AE7: =IF(OR(K7<=2,L7<=2),"Technical constraint dominates cost",IF(AB7=N7,"Cost and architecture align","Review coverage, power and support model")) -> Review coverage, power and support model
A8: Lux sensors | B8: Indoor multi-site | D8: 1 | E8: 70 | F8: 80 | G8: 25 | H8: 0.1 | I8: 8 | J8: 6 | K8: 5 | L8: 4 | M8: Periodic light level and threshold alarms | N8: LoRaWAN where a shared building network exists | O8: Medium | P8: =C8*(E8+G8+Assumptions!$B$13) -> 0 | Q8: =D8*Assumptions!$B$6*(Assumptions!$B$7+Assumptions!$B$8)+Assumptions!$B$5*(D8*Assumptions!$B$6*(Assumptions!$B$9+Assumptions!$B$10)+Assumptions!$B$12) -> 1125.8 | R8: =C8*E8*Assumptions!$B$19/100*Assumptions!$B$5+C8*IF(I8<=Assumptions!$B$5,Assumptions!$B$20,0) -> 0 | S8: =C8*Assumptions!$B$11*12*Assumptions!$B$5 -> 0 | T8: =SUM(P8:S8) -> 1125.8 | U8: =ROUND(T8/C8,2) -> #DIV/0! | V8: =C8*(F8+G8+Assumptions!$B$18+Assumptions!$B$15+Assumptions!$B$14*12*Assumptions!$B$5) -> 0 | W8: =ROUND(C8*MAX(0,H8-Assumptions!$B$16)*12*Assumptions!$B$5*Assumptions!$B$17,2) -> 0 | X8: =C8*F8*Assumptions!$B$19/100*Assumptions!$B$5+C8*IF(J8<=Assumptions!$B$5,Assumptions!$B$20,0) -> 0 | Y8: =SUM(V8:X8) -> 0 | Z8: =ROUND(Y8/C8,2) -> #DIV/0! | AA8: =ROUND(T8-Y8,2) -> 1125.8 | AB8: =IF(OR(K8<=2,L8<=2),"Not decisive",IF(T8<Y8,"LoRaWAN",IF(T8>Y8,"NB-IoT","Tie"))) -> NB-IoT | AC8: =ABS(T8-Y8)/MAX(T8,Y8) -> 1 | AD8: =IF((Z8-U8+Q8/C8)<=0,"N/A",ROUND((Q8/D8)/(Z8-U8+Q8/C8),0)) -> #DIV/0! | AE8: =IF(OR(K8<=2,L8<=2),"Technical constraint dominates cost",IF(AB8=N8,"Cost and architecture align","Review coverage, power and support model")) -> Review coverage, power and support model
A9: Metering — electricity and water | B9: Plantrooms / meters | D9: 1 | E9: 100 | F9: 110 | G9: 75 | H9: 0.3 | I9: 8 | J9: 6 | K9: 5 | L9: 5 | M9: Registers, pulse counts or Modbus data | N9: LoRaWAN for estates; NB-IoT for utility-style dispersed meters | O9: High | P9: =C9*(E9+G9+Assumptions!$B$13) -> 0 | Q9: =D9*Assumptions!$B$6*(Assumptions!$B$7+Assumptions!$B$8)+Assumptions!$B$5*(D9*Assumptions!$B$6*(Assumptions!$B$9+Assumptions!$B$10)+Assumptions!$B$12) -> 1125.8 | R9: =C9*E9*Assumptions!$B$19/100*Assumptions!$B$5+C9*IF(I9<=Assumptions!$B$5,Assumptions!$B$20,0) -> 0 | S9: =C9*Assumptions!$B$11*12*Assumptions!$B$5 -> 0 | T9: =SUM(P9:S9) -> 1125.8 | U9: =ROUND(T9/C9,2) -> #DIV/0! | V9: =C9*(F9+G9+Assumptions!$B$18+Assumptions!$B$15+Assumptions!$B$14*12*Assumptions!$B$5) -> 0 | W9: =ROUND(C9*MAX(0,H9-Assumptions!$B$16)*12*Assumptions!$B$5*Assumptions!$B$17,2) -> 0 | X9: =C9*F9*Assumptions!$B$19/100*Assumptions!$B$5+C9*IF(J9<=Assumptions!$B$5,Assumptions!$B$20,0) -> 0 | Y9: =SUM(V9:X9) -> 0 | Z9: =ROUND(Y9/C9,2) -> #DIV/0! | AA9: =ROUND(T9-Y9,2) -> 1125.8 | AB9: =IF(OR(K9<=2,L9<=2),"Not decisive",IF(T9<Y9,"LoRaWAN",IF(T9>Y9,"NB-IoT","Tie"))) -> NB-IoT | AC9: =ABS(T9-Y9)/MAX(T9,Y9) -> 1 | AD9: =IF((Z9-U9+Q9/C9)<=0,"N/A",ROUND((Q9/D9)/(Z9-U9+Q9/C9),0)) -> #DIV/0! | AE9: =IF(OR(K9<=2,L9<=2),"Technical constraint dominates cost",IF(AB9=N9,"Cost and architecture align","Review coverage, power and support model")) -> Review coverage, power and support model
A10: Fridge / process temperature | B10: Indoor critical assets | D10: 1 | E10: 70 | F10: 76 | G10: 45 | H10: 0.5 | I10: 8 | J10: 6 | K10: 5 | L10: 5 | M10: Periodic temperature plus immediate excursion alarm | N10: Either; preserve local logging and alarm path | O10: High | P10: =C10*(E10+G10+Assumptions!$B$13) -> 0 | Q10: =D10*Assumptions!$B$6*(Assumptions!$B$7+Assumptions!$B$8)+Assumptions!$B$5*(D10*Assumptions!$B$6*(Assumptions!$B$9+Assumptions!$B$10)+Assumptions!$B$12) -> 1125.8 | R10: =C10*E10*Assumptions!$B$19/100*Assumptions!$B$5+C10*IF(I10<=Assumptions!$B$5,Assumptions!$B$20,0) -> 0 | S10: =C10*Assumptions!$B$11*12*Assumptions!$B$5 -> 0 | T10: =SUM(P10:S10) -> 1125.8 | U10: =ROUND(T10/C10,2) -> #DIV/0! | V10: =C10*(F10+G10+Assumptions!$B$18+Assumptions!$B$15+Assumptions!$B$14*12*Assumptions!$B$5) -> 0 | W10: =ROUND(C10*MAX(0,H10-Assumptions!$B$16)*12*Assumptions!$B$5*Assumptions!$B$17,2) -> 0 | X10: =C10*F10*Assumptions!$B$19/100*Assumptions!$B$5+C10*IF(J10<=Assumptions!$B$5,Assumptions!$B$20,0) -> 0 | Y10: =SUM(V10:X10) -> 0 | Z10: =ROUND(Y10/C10,2) -> #DIV/0! | AA10: =ROUND(T10-Y10,2) -> 1125.8 | AB10: =IF(OR(K10<=2,L10<=2),"Not decisive",IF(T10<Y10,"LoRaWAN",IF(T10>Y10,"NB-IoT","Tie"))) -> NB-IoT | AC10: =ABS(T10-Y10)/MAX(T10,Y10) -> 1 | AD10: =IF((Z10-U10+Q10/C10)<=0,"N/A",ROUND((Q10/D10)/(Z10-U10+Q10/C10),0)) -> #DIV/0! | AE10: =IF(OR(K10<=2,L10<=2),"Technical constraint dominates cost",IF(AB10=N10,"Cost and architecture align","Review coverage, power and support model")) -> Review coverage, power and support model
A11: Waste water monitoring | B11: Remote outdoor assets | D11: 1 | E11: 300 | F11: 320 | G11: 250 | H11: 1 | I11: 5 | J11: 4 | K11: 4 | L11: 5 | M11: Level/quality/status metadata; no raw waveforms | N11: NB-IoT usually favoured for dispersed remote assets | O11: Medium | P11: =C11*(E11+G11+Assumptions!$B$13) -> 0 | Q11: =D11*Assumptions!$B$6*(Assumptions!$B$7+Assumptions!$B$8)+Assumptions!$B$5*(D11*Assumptions!$B$6*(Assumptions!$B$9+Assumptions!$B$10)+Assumptions!$B$12) -> 1125.8 | R11: =C11*E11*Assumptions!$B$19/100*Assumptions!$B$5+C11*IF(I11<=Assumptions!$B$5,Assumptions!$B$20,0) -> 0 | S11: =C11*Assumptions!$B$11*12*Assumptions!$B$5 -> 0 | T11: =SUM(P11:S11) -> 1125.8 | U11: =ROUND(T11/C11,2) -> #DIV/0! | V11: =C11*(F11+G11+Assumptions!$B$18+Assumptions!$B$15+Assumptions!$B$14*12*Assumptions!$B$5) -> 0 | W11: =ROUND(C11*MAX(0,H11-Assumptions!$B$16)*12*Assumptions!$B$5*Assumptions!$B$17,2) -> 0 | X11: =C11*F11*Assumptions!$B$19/100*Assumptions!$B$5+C11*IF(J11<=Assumptions!$B$5,Assumptions!$B$20,0) -> 0 | Y11: =SUM(V11:X11) -> 0 | Z11: =ROUND(Y11/C11,2) -> #DIV/0! | AA11: =ROUND(T11-Y11,2) -> 1125.8 | AB11: =IF(OR(K11<=2,L11<=2),"Not decisive",IF(T11<Y11,"LoRaWAN",IF(T11>Y11,"NB-IoT","Tie"))) -> NB-IoT | AC11: =ABS(T11-Y11)/MAX(T11,Y11) -> 1 | AD11: =IF((Z11-U11+Q11/C11)<=0,"N/A",ROUND((Q11/D11)/(Z11-U11+Q11/C11),0)) -> #DIV/0! | AE11: =IF(OR(K11<=2,L11<=2),"Technical constraint dominates cost",IF(AB11=N11,"Cost and architecture align","Review coverage, power and support model")) -> Review coverage, power and support model
A12: Water temperature | B12: Remote / plantroom | D12: 1 | E12: 85 | F12: 95 | G12: 70 | H12: 0.3 | I12: 8 | J12: 6 | K12: 5 | L12: 5 | M12: Periodic readings and threshold alarms | N12: Either; LoRaWAN when sites share coverage | O12: High | P12: =C12*(E12+G12+Assumptions!$B$13) -> 0 | Q12: =D12*Assumptions!$B$6*(Assumptions!$B$7+Assumptions!$B$8)+Assumptions!$B$5*(D12*Assumptions!$B$6*(Assumptions!$B$9+Assumptions!$B$10)+Assumptions!$B$12) -> 1125.8 | R12: =C12*E12*Assumptions!$B$19/100*Assumptions!$B$5+C12*IF(I12<=Assumptions!$B$5,Assumptions!$B$20,0) -> 0 | S12: =C12*Assumptions!$B$11*12*Assumptions!$B$5 -> 0 | T12: =SUM(P12:S12) -> 1125.8 | U12: =ROUND(T12/C12,2) -> #DIV/0! | V12: =C12*(F12+G12+Assumptions!$B$18+Assumptions!$B$15+Assumptions!$B$14*12*Assumptions!$B$5) -> 0 | W12: =ROUND(C12*MAX(0,H12-Assumptions!$B$16)*12*Assumptions!$B$5*Assumptions!$B$17,2) -> 0 | X12: =C12*F12*Assumptions!$B$19/100*Assumptions!$B$5+C12*IF(J12<=Assumptions!$B$5,Assumptions!$B$20,0) -> 0 | Y12: =SUM(V12:X12) -> 0 | Z12: =ROUND(Y12/C12,2) -> #DIV/0! | AA12: =ROUND(T12-Y12,2) -> 1125.8 | AB12: =IF(OR(K12<=2,L12<=2),"Not decisive",IF(T12<Y12,"LoRaWAN",IF(T12>Y12,"NB-IoT","Tie"))) -> NB-IoT | AC12: =ABS(T12-Y12)/MAX(T12,Y12) -> 1 | AD12: =IF((Z12-U12+Q12/C12)<=0,"N/A",ROUND((Q12/D12)/(Z12-U12+Q12/C12),0)) -> #DIV/0! | AE12: =IF(OR(K12<=2,L12<=2),"Technical constraint dominates cost",IF(AB12=N12,"Cost and architecture align","Review coverage, power and support model")) -> Review coverage, power and support model
A13: Water flow | B13: Remote / plantroom | D13: 1 | E13: 100 | F13: 110 | G13: 90 | H13: 0.5 | I13: 8 | J13: 6 | K13: 5 | L13: 5 | M13: Pulse/flow total and anomaly alarm | N13: Either; NB-IoT is simpler when widely dispersed | O13: High | P13: =C13*(E13+G13+Assumptions!$B$13) -> 0 | Q13: =D13*Assumptions!$B$6*(Assumptions!$B$7+Assumptions!$B$8)+Assumptions!$B$5*(D13*Assumptions!$B$6*(Assumptions!$B$9+Assumptions!$B$10)+Assumptions!$B$12) -> 1125.8 | R13: =C13*E13*Assumptions!$B$19/100*Assumptions!$B$5+C13*IF(I13<=Assumptions!$B$5,Assumptions!$B$20,0) -> 0 | S13: =C13*Assumptions!$B$11*12*Assumptions!$B$5 -> 0 | T13: =SUM(P13:S13) -> 1125.8 | U13: =ROUND(T13/C13,2) -> #DIV/0! | V13: =C13*(F13+G13+Assumptions!$B$18+Assumptions!$B$15+Assumptions!$B$14*12*Assumptions!$B$5) -> 0 | W13: =ROUND(C13*MAX(0,H13-Assumptions!$B$16)*12*Assumptions!$B$5*Assumptions!$B$17,2) -> 0 | X13: =C13*F13*Assumptions!$B$19/100*Assumptions!$B$5+C13*IF(J13<=Assumptions!$B$5,Assumptions!$B$20,0) -> 0 | Y13: =SUM(V13:X13) -> 0 | Z13: =ROUND(Y13/C13,2) -> #DIV/0! | AA13: =ROUND(T13-Y13,2) -> 1125.8 | AB13: =IF(OR(K13<=2,L13<=2),"Not decisive",IF(T13<Y13,"LoRaWAN",IF(T13>Y13,"NB-IoT","Tie"))) -> NB-IoT | AC13: =ABS(T13-Y13)/MAX(T13,Y13) -> 1 | AD13: =IF((Z13-U13+Q13/C13)<=0,"N/A",ROUND((Q13/D13)/(Z13-U13+Q13/C13),0)) -> #DIV/0! | AE13: =IF(OR(K13<=2,L13<=2),"Technical constraint dominates cost",IF(AB13=N13,"Cost and architecture align","Review coverage, power and support model")) -> Review coverage, power and support model
A14: Water leak detection | B14: Indoor dense estate | D14: 1 | E14: 65 | F14: 75 | G14: 30 | H14: 0.1 | I14: 5 | J14: 4 | K14: 5 | L14: 5 | M14: Immediate event; local shut-off must not depend on cloud | N14: LoRaWAN for density; NB-IoT for standalone premises | O14: High | P14: =C14*(E14+G14+Assumptions!$B$13) -> 0 | Q14: =D14*Assumptions!$B$6*(Assumptions!$B$7+Assumptions!$B$8)+Assumptions!$B$5*(D14*Assumptions!$B$6*(Assumptions!$B$9+Assumptions!$B$10)+Assumptions!$B$12) -> 1125.8 | R14: =C14*E14*Assumptions!$B$19/100*Assumptions!$B$5+C14*IF(I14<=Assumptions!$B$5,Assumptions!$B$20,0) -> 0 | S14: =C14*Assumptions!$B$11*12*Assumptions!$B$5 -> 0 | T14: =SUM(P14:S14) -> 1125.8 | U14: =ROUND(T14/C14,2) -> #DIV/0! | V14: =C14*(F14+G14+Assumptions!$B$18+Assumptions!$B$15+Assumptions!$B$14*12*Assumptions!$B$5) -> 0 | W14: =ROUND(C14*MAX(0,H14-Assumptions!$B$16)*12*Assumptions!$B$5*Assumptions!$B$17,2) -> 0 | X14: =C14*F14*Assumptions!$B$19/100*Assumptions!$B$5+C14*IF(J14<=Assumptions!$B$5,Assumptions!$B$20,0) -> 0 | Y14: =SUM(V14:X14) -> 0 | Z14: =ROUND(Y14/C14,2) -> #DIV/0! | AA14: =ROUND(T14-Y14,2) -> 1125.8 | AB14: =IF(OR(K14<=2,L14<=2),"Not decisive",IF(T14<Y14,"LoRaWAN",IF(T14>Y14,"NB-IoT","Tie"))) -> NB-IoT | AC14: =ABS(T14-Y14)/MAX(T14,Y14) -> 1 | AD14: =IF((Z14-U14+Q14/C14)<=0,"N/A",ROUND((Q14/D14)/(Z14-U14+Q14/C14),0)) -> #DIV/0! | AE14: =IF(OR(K14<=2,L14<=2),"Technical constraint dominates cost",IF(AB14=N14,"Cost and architecture align","Review coverage, power and support model")) -> Review coverage, power and support model
A15: Acoustic sensors | B15: Water / machinery | D15: 1 | E15: 150 | F15: 165 | G15: 80 | H15: 2 | I15: 5 | J15: 4 | K15: 4 | L15: 5 | M15: Edge-derived dB/features only; raw audio is unsuitable | N15: NB-IoT for dispersed water loggers; either on campus | O15: Medium | P15: =C15*(E15+G15+Assumptions!$B$13) -> 0 | Q15: =D15*Assumptions!$B$6*(Assumptions!$B$7+Assumptions!$B$8)+Assumptions!$B$5*(D15*Assumptions!$B$6*(Assumptions!$B$9+Assumptions!$B$10)+Assumptions!$B$12) -> 1125.8 | R15: =C15*E15*Assumptions!$B$19/100*Assumptions!$B$5+C15*IF(I15<=Assumptions!$B$5,Assumptions!$B$20,0) -> 0 | S15: =C15*Assumptions!$B$11*12*Assumptions!$B$5 -> 0 | T15: =SUM(P15:S15) -> 1125.8 | U15: =ROUND(T15/C15,2) -> #DIV/0! | V15: =C15*(F15+G15+Assumptions!$B$18+Assumptions!$B$15+Assumptions!$B$14*12*Assumptions!$B$5) -> 0 | W15: =ROUND(C15*MAX(0,H15-Assumptions!$B$16)*12*Assumptions!$B$5*Assumptions!$B$17,2) -> 0 | X15: =C15*F15*Assumptions!$B$19/100*Assumptions!$B$5+C15*IF(J15<=Assumptions!$B$5,Assumptions!$B$20,0) -> 0 | Y15: =SUM(V15:X15) -> 0 | Z15: =ROUND(Y15/C15,2) -> #DIV/0! | AA15: =ROUND(T15-Y15,2) -> 1125.8 | AB15: =IF(OR(K15<=2,L15<=2),"Not decisive",IF(T15<Y15,"LoRaWAN",IF(T15>Y15,"NB-IoT","Tie"))) -> NB-IoT | AC15: =ABS(T15-Y15)/MAX(T15,Y15) -> 1 | AD15: =IF((Z15-U15+Q15/C15)<=0,"N/A",ROUND((Q15/D15)/(Z15-U15+Q15/C15),0)) -> #DIV/0! | AE15: =IF(OR(K15<=2,L15<=2),"Technical constraint dominates cost",IF(AB15=N15,"Cost and architecture align","Review coverage, power and support model")) -> Review coverage, power and support model
A16: Bin fill level — ultrasonic | B16: Distributed bins | D16: 1 | E16: 124 | F16: 124 | G16: 75 | H16: 0.2 | I16: 8 | J16: 6 | K16: 5 | L16: 5 | M16: Distance/fill percentage and alarms | N16: NB-IoT for citywide assets; LoRaWAN on campus/private estate | O16: High | P16: =C16*(E16+G16+Assumptions!$B$13) -> 0 | Q16: =D16*Assumptions!$B$6*(Assumptions!$B$7+Assumptions!$B$8)+Assumptions!$B$5*(D16*Assumptions!$B$6*(Assumptions!$B$9+Assumptions!$B$10)+Assumptions!$B$12) -> 1125.8 | R16: =C16*E16*Assumptions!$B$19/100*Assumptions!$B$5+C16*IF(I16<=Assumptions!$B$5,Assumptions!$B$20,0) -> 0 | S16: =C16*Assumptions!$B$11*12*Assumptions!$B$5 -> 0 | T16: =SUM(P16:S16) -> 1125.8 | U16: =ROUND(T16/C16,2) -> #DIV/0! | V16: =C16*(F16+G16+Assumptions!$B$18+Assumptions!$B$15+Assumptions!$B$14*12*Assumptions!$B$5) -> 0 | W16: =ROUND(C16*MAX(0,H16-Assumptions!$B$16)*12*Assumptions!$B$5*Assumptions!$B$17,2) -> 0 | X16: =C16*F16*Assumptions!$B$19/100*Assumptions!$B$5+C16*IF(J16<=Assumptions!$B$5,Assumptions!$B$20,0) -> 0 | Y16: =SUM(V16:X16) -> 0 | Z16: =ROUND(Y16/C16,2) -> #DIV/0! | AA16: =ROUND(T16-Y16,2) -> 1125.8 | AB16: =IF(OR(K16<=2,L16<=2),"Not decisive",IF(T16<Y16,"LoRaWAN",IF(T16>Y16,"NB-IoT","Tie"))) -> NB-IoT | AC16: =ABS(T16-Y16)/MAX(T16,Y16) -> 1 | AD16: =IF((Z16-U16+Q16/C16)<=0,"N/A",ROUND((Q16/D16)/(Z16-U16+Q16/C16),0)) -> #DIV/0! | AE16: =IF(OR(K16<=2,L16<=2),"Technical constraint dominates cost",IF(AB16=N16,"Cost and architecture align","Review coverage, power and support model")) -> Review coverage, power and support model
A17: Optical bin sensors / computer vision | B17: Distributed bins | D17: 1 | E17: 450 | F17: 475 | G17: 180 | H17: 5 | I17: 4 | J17: 3 | K17: 2 | L17: 2 | M17: On-device inference only; do not send images over LPWAN | N17: Use LTE-M/LTE/5G if images are required; LPWAN only for metadata | O17: Low | P17: =C17*(E17+G17+Assumptions!$B$13) -> 0 | Q17: =D17*Assumptions!$B$6*(Assumptions!$B$7+Assumptions!$B$8)+Assumptions!$B$5*(D17*Assumptions!$B$6*(Assumptions!$B$9+Assumptions!$B$10)+Assumptions!$B$12) -> 1125.8 | R17: =C17*E17*Assumptions!$B$19/100*Assumptions!$B$5+C17*IF(I17<=Assumptions!$B$5,Assumptions!$B$20,0) -> 0 | S17: =C17*Assumptions!$B$11*12*Assumptions!$B$5 -> 0 | T17: =SUM(P17:S17) -> 1125.8 | U17: =ROUND(T17/C17,2) -> #DIV/0! | V17: =C17*(F17+G17+Assumptions!$B$18+Assumptions!$B$15+Assumptions!$B$14*12*Assumptions!$B$5) -> 0 | W17: =ROUND(C17*MAX(0,H17-Assumptions!$B$16)*12*Assumptions!$B$5*Assumptions!$B$17,2) -> 0 | X17: =C17*F17*Assumptions!$B$19/100*Assumptions!$B$5+C17*IF(J17<=Assumptions!$B$5,Assumptions!$B$20,0) -> 0 | Y17: =SUM(V17:X17) -> 0 | Z17: =ROUND(Y17/C17,2) -> #DIV/0! | AA17: =ROUND(T17-Y17,2) -> 1125.8 | AB17: =IF(OR(K17<=2,L17<=2),"Not decisive",IF(T17<Y17,"LoRaWAN",IF(T17>Y17,"NB-IoT","Tie"))) -> Not decisive | AC17: =ABS(T17-Y17)/MAX(T17,Y17) -> 1 | AD17: =IF((Z17-U17+Q17/C17)<=0,"N/A",ROUND((Q17/D17)/(Z17-U17+Q17/C17),0)) -> #DIV/0! | AE17: =IF(OR(K17<=2,L17<=2),"Technical constraint dominates cost",IF(AB17=N17,"Cost and architecture align","Review coverage, power and support model")) -> Technical constraint dominates cost
... A20: Ultrasonic non-invasive — medical gases | B20: Clinical cylinders / pipes | D20: 1 | E20: 180 | F20: 195 | G20: 200 | H20: 0.5 | I20: 6 | J20: 5 | K20: 4 | L20: 4 | M20: Secondary level/flow telemetry with local fail-safe | N20: Either as supplementary telemetry; validate clinical compliance | O20: Low | P20: =C20*(E20+G20+Assumptions!$B$13) -> 0 | Q20: =D20*Assumptions!$B$6*(Assumptions!$B$7+Assumptions!$B$8)+Assumptions!$B$5*(D20*Assumptions!$B$6*(Assumptions!$B$9+Assumptions!$B$10)+Assumptions!$B$12) -> 1125.8 | R20: =C20*E20*Assumptions!$B$19/100*Assumptions!$B$5+C20*IF(I20<=Assumptions!$B$5,Assumptions!$B$20,0) -> 0 | S20: =C20*Assumptions!$B$11*12*Assumptions!$B$5 -> 0 | T20: =SUM(P20:S20) -> 1125.8 | U20: =ROUND(T20/C20,2) -> #DIV/0! | V20: =C20*(F20+G20+Assumptions!$B$18+Assumptions!$B$15+Assumptions!$B$14*12*Assumptions!$B$5) -> 0 | W20: =ROUND(C20*MAX(0,H20-Assumptions!$B$16)*12*Assumptions!$B$5*Assumptions!$B$17,2) -> 0 | X20: =C20*F20*Assumptions!$B$19/100*Assumptions!$B$5+C20*IF(J20<=Assumptions!$B$5,Assumptions!$B$20,0) -> 0 | Y20: =SUM(V20:X20) -> 0 | Z20: =ROUND(Y20/C20,2) -> #DIV/0! | AA20: =ROUND(T20-Y20,2) -> 1125.8 | AB20: =IF(OR(K20<=2,L20<=2),"Not decisive",IF(T20<Y20,"LoRaWAN",IF(T20>Y20,"NB-IoT","Tie"))) -> NB-IoT | AC20: =ABS(T20-Y20)/MAX(T20,Y20) -> 1 | AD20: =IF((Z20-U20+Q20/C20)<=0,"N/A",ROUND((Q20/D20)/(Z20-U20+Q20/C20),0)) -> #DIV/0! | AE20: =IF(OR(K20<=2,L20<=2),"Technical constraint dominates cost",IF(AB20=N20,"Cost and architecture align","Review coverage, power and support model")) -> Review coverage, power and support model

Sheet Decision Guide
A1: Decision Guide | B1: Decision Guide | C1: Decision Guide | D1: Decision Guide | E1: Decision Guide | F1: Decision Guide
A2: Cost follows architecture. Apply these gates before accepting the cheapest five-year TCO. | B2: Cost follows architecture. Apply these gates before accepting the cheapest five-year TCO. | C2: Cost follows architecture. Apply these gates before accepting the cheapest five-year TCO. | D2: Cost follows architecture. Apply these gates before accepting the cheapest five-year TCO. | E2: Cost follows architecture. Apply these gates before accepting the cheapest five-year TCO. | F2: Cost follows architecture. Apply these gates before accepting the cheapest five-year TCO.
A4: Question | B4: LoRaWAN signal | C4: NB-IoT signal | D4: Preferred direction | E4: Risk / caveat | F4: Action
A5: Are devices concentrated in owned buildings/campus? | B5: Strong | C5: Neutral | D5: LoRaWAN | E5: Gateway resilience and backhaul become your responsibility | F5: RF survey; test plantrooms, basements and risers
A6: Are devices geographically dispersed? | B6: Weak unless public LoRaWAN exists | C6: Strong | D6: NB-IoT | E6: Coverage is operator-dependent and can vary indoors/underground | F6: Check carrier coverage and test with target SIM/device
A7: Is payload small and infrequent? | B7: Strong | C7: Strong | D7: Either | E7: Frequent downlinks reduce battery life | F7: Define bytes/message, messages/day and alarm bursts
A8: Are images, video, raw audio or raw waveforms required? | B8: Unsuitable | C8: Usually unsuitable | D8: LTE-M/LTE/5G/Wi-Fi/wired | E8: Edge processing may turn raw data into tiny metadata | F8: Specify raw vs edge-derived data explicitly
A9: Is an immediate local safety action required? | B9: Cloud path insufficient | C9: Cloud path insufficient | D9: Local/wired fail-safe | E9: LPWAN latency, outage and battery state cannot be the sole safety layer | F9: Keep local control and use LPWAN for supervisory telemetry
A10: Will a battery visit be expensive? | B10: Often strongest | C10: Good | D10: Compare tested battery life | E10: Coverage enhancement and retry behaviour can dominate battery life | F10: Pilot in worst-case radio locations
A11: Do you require two-way frequent control? | B11: Limited downlink capacity | C11: Better but still LPWA | D11: Consider LTE-M/Wi-Fi/wired | E11: Battery and latency may be unacceptable | F11: Define latency, acknowledgement and retry requirements
A12: Do you need to avoid local infrastructure? | B12: No | C12: Yes | D12: NB-IoT | E12: Recurring carrier/vendor dependency replaces gateway ownership | F12: Review contract, roaming and exit strategy
A15: Suitability score: 5 = natural fit; 4 = good fit; 3 = conditional; 2 = major constraint; 1 = unsuitable for the stated behaviour. | B15: Suitability score: 5 = natural fit; 4 = good fit; 3 = conditional; 2 = major constraint; 1 = unsuitable for the stated behaviour. | C15: Suitability score: 5 = natural fit; 4 = good fit; 3 = conditional; 2 = major constraint; 1 = unsuitable for the stated behaviour. | D15: Suitability score: 5 = natural fit; 4 = good fit; 3 = conditional; 2 = major constraint; 1 = unsuitable for the stated behaviour. | E15: Suitability score: 5 = natural fit; 4 = good fit; 3 = conditional; 2 = major constraint; 1 = unsuitable for the stated behaviour. | F15: Suitability score: 5 = natural fit; 4 = good fit; 3 = conditional; 2 = major constraint; 1 = unsuitable for the stated behaviour.

Sheet Sources
A1: Sources & Evidence Log | B1: Sources & Evidence Log | C1: Sources & Evidence Log | D1: Sources & Evidence Log | E1: Sources & Evidence Log | F1: Sources & Evidence Log
A2: Public sources support the benchmark and technical boundaries. Vendor quotations should replace indicative prices before procurement. | B2: Public sources support the benchmark and technical boundaries. Vendor quotations should replace indicative prices before procurement. | C2: Public sources support the benchmark and technical boundaries. Vendor quotations should replace indicative prices before procurement. | D2: Public sources support the benchmark and technical boundaries. Vendor quotations should replace indicative prices before procurement. | E2: Public sources support the benchmark and technical boundaries. Vendor quotations should replace indicative prices before procurement. | F2: Public sources support the benchmark and technical boundaries. Vendor quotations should replace indicative prices before procurement.
A4: Topic | B4: Evidence used | C4: URL | D4: Accessed | E4: Type | F4: Model impact
A5: NB-IoT tariff | B5: £0.98/device/month plus £0.70 one-off; includes 17 MB/device/month | D5: =DATE(2026,7,31) -> 46234 | E5: User input | F5: NB recurring connectivity, one-off fee and included-data inputs
A6: NB-IoT overage | B6: £0.01/MB above 17 MB/device/month | D6: =DATE(2026,7,31) -> 46234 | E6: User input | F6: NB monthly data-overage formula
A7: GBP/EUR | B7: ECB reference rate: £0.85388 per €1 on 24 Jul 2026 | C7: https://www.ecb.europa.eu/stats/policy_and_exchange_rates/euro_reference_exchange_rates/html/index.en.html | D7: 46230 | E7: Official | F7: Currency conversion
A8: UK NB-IoT reach | B8: BT/EE announced NB-IoT coverage of 97% of UK population | C8: https://newsroom.bt.com/bt-launches-multi-million-pound-nb-iot-network-to-support-uk-smart-cities/ | D8: 46230 | E8: Operator primary | F8: Supports dispersed-asset option; location testing still required
A9: UK NB-IoT use case | B9: Vodafone NB-IoT supports leak detection without Wi-Fi | C9: https://www.vodafone.co.uk/business/case-studies/leaksafe-and-vodafone-business-narrowband-iot | D9: 46230 | E9: Operator primary | F9: Leak detection fit
A10: Acoustic water logging | B10: Vodafone says NB-IoT improved underground reach and power versus 3G/4G | C10: https://www.vodafone.co.uk/business/case-studies/nb-iot-gutermann | D10: 46230 | E10: Operator primary | F10: Acoustic/dispersed water fit
A11: NB-IoT bandwidth boundary | B11: Vodafone describes NB-IoT as supporting small amounts of data | C11: https://www.vodafone.co.uk/business/iot/iot-faqs | D11: 46230 | E11: Operator primary | F11: Excludes video/raw high-rate data
A12: LoRaWAN smart buildings | B12: LoRa Alliance identifies environmental, leak, occupancy, metering and predictive-maintenance applications | C12: https://lora-alliance.org/buildings-vertical-market/ | D12: 46230 | E12: Industry body | F12: Building/campus suitability
A13: LoRaWAN/NB-IoT comparison | B13: LoRaWAN evidence for smart buildings and utilities | C13: https://lora-alliance.org/wp-content/uploads/2020/11/cr-lora-102_lorawanr_and_nb-iot.pdf | D13: 46230 | E13: Industry white paper | F13: Category fit scoring
A14: LoRa gateway | B14: UG65 supports indoor deployments and up to 2,000 devices | C14: https://www.milesight.com/iot/product/lorawan-gateway/ug65 | D14: 46230 | E14: Vendor primary | F14: Gateway capacity assumption
A15: UK device/gateway pricing | B15: Public UK prices for LoRaWAN, NB-IoT sensors and gateways | C15: https://ukiot.io/shop/ | D15: 46230 | E15: Distributor | F15: Hardware planning benchmarks
A16: LoRaWAN server | B16: The Things Stack provides managed cloud and free discovery tier | C16: https://www.thethingsindustries.com/stack/plans/ | D16: 46230 | E16: Vendor primary | F16: Network-server architecture
A17: LoRaWAN server price anchor | B17: AWS Marketplace lists $0.336/hour to register up to 1,000 devices | C17: https://aws.amazon.com/marketplace/pp/prodview-djx65iyt6w5cy | D17: 46230 | E17: Marketplace | F17: £0.20/device/month planning benchmark at scale
A18: LPWA comparison | B18: GSMA compares bandwidth, latency, battery, spectrum and module cost across NB-IoT and LoRaWAN | C18: https://www.gsma.com/solutions-and-impact/connectivity-for-good/mobile-for-development/wp-content/uploads/2023/04/IoT-for-Development-Use-cases-delivering-impact.pdf | D18: 46230 | E18: Industry body | F18: Technical decision gates
